<xml id="toolbox" style="display: none">
    <category name="Logic" colour="210">
        <block type="controls_if"></block>
        <block type="logic_compare"></block>
        <block type="logic_operation"></block>
        <block type="logic_negate"></block>
        <block type="logic_boolean"></block>
        <block type="logic_null"></block>
        <block type="logic_ternary"></block>
        <block type="logic_operation_and"></block>
        <block type="logic_operation_or"></block>
    </category>
    <category name="Loops" colour="120">
        <block type="controls_repeat_ext">
            <value name="TIMES">
                <shadow type="math_number">
                    <field name="NUM">10</field>
                </shadow>
            </value>
        </block>
        <block type="controls_whileUntil"></block>
        <block type="controls_for">
            <value name="FROM">
                <shadow type="math_number">
                    <field name="NUM">1</field>
                </shadow>
            </value>
            <value name="TO">
                <shadow type="math_number">
                    <field name="NUM">10</field>
                </shadow>
            </value>
            <value name="BY">
                <shadow type="math_number">
                    <field name="NUM">1</field>
                </shadow>
            </value>
        </block>
        <block type="controls_flow_statements"></block>
    </category>
    <category name="Arrays" colour="#745BA5">
        <block type="typed_arrays_create_with"></block>
        <block type="typed_arrays_setIndex"></block>
        <block type="typed_arrays_getIndex"></block>
        <block type="typed_arrays_delete"></block>
    </category>
    <category name="Math" colour="230">
        <block type="math_number" gap="32"></block>
        <block type="math_arithmetic">
            <value name="A">
                <shadow type="math_number">
                    <field name="NUM">1</field>
                </shadow>
            </value>
            <value name="B">
                <shadow type="math_number">
                    <field name="NUM">1</field>
                </shadow>
            </value>
        </block>
        <block type="math_single">
            <value name="NUM">
                <shadow type="math_number">
                    <field name="NUM">9</field>
                </shadow>
            </value>
        </block>
        <block type="math_trig">
            <value name="NUM">
                <shadow type="math_number">
                    <field name="NUM">45</field>
                </shadow>
            </value>
        </block>
        <block type="math_constant"></block>
        <block type="math_change">
            <value name="DELTA">
                <shadow type="math_number">
                    <field name="NUM">1</field>
                </shadow>
            </value>
        </block>
        <block type="math_round">
            <value name="NUM">
                <shadow type="math_number">
                    <field name="NUM">3.1</field>
                </shadow>
            </value>
        </block>
        <block type="math_modulo">
            <value name="DIVIDEND">
                <shadow type="math_number">
                    <field name="NUM">64</field>
                </shadow>
            </value>
            <value name="DIVISOR">
                <shadow type="math_number">
                    <field name="NUM">10</field>
                </shadow>
            </value>
        </block>
        <block type="math_constrain">
            <value name="VALUE">
                <shadow type="math_number">
                    <field name="NUM">50</field>
                </shadow>
            </value>
            <value name="LOW">
                <shadow type="math_number">
                    <field name="NUM">1</field>
                </shadow>
            </value>
            <value name="HIGH">
                <shadow type="math_number">
                    <field name="NUM">100</field>
                </shadow>
            </value>
        </block>
        <block type="math_random_int">
            <value name="FROM">
                <shadow type="math_number">
                    <field name="NUM">1</field>
                </shadow>
            </value>
            <value name="TO">
                <shadow type="math_number">
                    <field name="NUM">100</field>
                </shadow>
            </value>
        </block>
        <block type="arduino_math_map">
            <value name="VALUE">
                <shadow type="math_number">
                    <field name="NUM">0</field>
                </shadow>
            </value>
            <value name="FROM_LOW">
                <shadow type="math_number">
                    <field name="NUM">0</field>
                </shadow>
            </value>
            <value name="FROM_HIGH">
                <shadow type="math_number">
                    <field name="NUM">0</field>
                </shadow>
            </value>
            <value name="TO_LOW">
                <shadow type="math_number">
                    <field name="NUM">0</field>
                </shadow>
            </value>
            <value name="TO_HIGH">
                <shadow type="math_number">
                    <field name="NUM">0</field>
                </shadow>
            </value>
        </block>
        <block type="arduino_random_seed">
            <value name="SEED">
                <shadow type="analog_read">
                    <value name="PIN">
                        <shadow type="math_number">
                            <field name="NUM">0</field>
                        </shadow>
                    </value>
                </shadow>
            </value>
        </block>
        <block type="arduino_random">
            <value name="MIN">
                <shadow type="math_number">
                    <field name="NUM">0</field>
                </shadow>
            </value>
            <value name="MAX">
                <shadow type="math_number">
                    <field name="NUM">0</field>
                </shadow>
            </value>
        </block>
        <block type="arduino_srand">
            <value name="SEED">
                <shadow type="math_number">
                    <field name="NUM">0</field>
                </shadow>
            </value>
        </block>
    </category>
    <sep></sep>
    <category name="Time" colour="#726dc5" enabled="false">
        <block type="delayseconds">
            <value name="SECONDS">
                <shadow type="math_number">
                    <field name="NUM">0</field>
                </shadow>
            </value>
        </block>
        <block type="delayms">
            <value name="MILLISECONDS">
                <shadow type="math_number">
                    <field name="NUM">0</field>
                </shadow>
            </value>
        </block>
        <block type="delaymicroseconds">
            <value name="MICROSECONDS">
                <shadow type="math_number">
                    <field name="NUM">0</field>
                </shadow>
            </value>
        </block>
        <block type="seconds"></block>
        <block type="milliseconds"></block>
        <block type="microseconds"></block>
    </category>
    <category name="Digital I/O" colour="#4d6bc4">
        <block type="pininput">
            <value name='PIN'>
                <shadow type="math_number">
                    <field name="NUM">0</field>
                </shadow>
            </value>
        </block>
        <block type="digitalwrite">
            <value name="PIN">
                <shadow type="math_number">
                    <field name="NUM">0</field>
                </shadow>
            </value>
        </block>
        <block type="digital_read">
            <value name="PIN">
                <shadow type="math_number">
                    <field name="NUM">0</field>
                </shadow>
            </value>
        </block>
    </category>
    <category name="Analog I/O" colour="#439bbc">
        <block type="analog_reference"></block>
        <block type="analog_read">
            <value name="PIN">
                <shadow type="math_number">
                    <field name="NUM">0</field>
                </shadow>
            </value>
        </block>
        <block type="analog_write">
            <value name="VALUE">
                <shadow type="math_number">
                    <field name="NUM">0</field>
                </shadow>
            </value>
            <value name="PIN">
                <shadow type="math_number">
                    <field name="NUM">0</field>
                </shadow>
            </value>
        </block>
    </category>
    <category name="Advanced I/O" colour="#2c897f">
        <block type="tone_pin_freq">
            <value name="FREQUENCY">
                <shadow type="math_number">
                    <field name="NUM">0</field>
                </shadow>
            </value>
            <value name="PIN">
                <shadow type="math_number">
                    <field name="NUM">0</field>
                </shadow>
            </value>
        </block>
        <block type="tone_pin_freq_duration">
            <value name="FREQUENCY">
                <shadow type="math_number">
                    <field name="NUM">0</field>
                </shadow>
            </value>
            <value name="PIN">
                <shadow type="math_number">
                    <field name="NUM">0</field>
                </shadow>
            </value>
            <value name="DURATION">
                <shadow type="math_number">
                    <field name="NUM">0</field>
                </shadow>
            </value>
        </block>
        <block type="advanced_io_pulse_in">
            <value name="PIN">
                <shadow type="math_number">
                    <field name="NUM">0</field>
                </shadow>
            </value>
        </block>
        <block type="advanced_io_pulse_in_timeout">
            <value name="PIN">
                <shadow type="math_number">
                    <field name="NUM">0</field>
                </shadow>
            </value>
            <value name="TIMEOUT">
                <shadow type="math_number">
                    <field name="NUM">1000</field>
                </shadow>
            </value>
        </block>
        <block type="advanced_io_pulse_in_long">
            <value name="PIN">
                <shadow type="math_number">
                    <field name="NUM">0</field>
                </shadow>
            </value>
        </block>
        <block type="advanced_io_pulse_in_long_timeout">
            <value name="PIN">
                <shadow type="math_number">
                    <field name="NUM">0</field>
                </shadow>
            </value>
            <value name="TIMEOUT">
                <shadow type="math_number">
                    <field name="NUM">1000</field>
                </shadow>
            </value>
        </block>
        <block type="advanced_io_shift_in">
            <value name="DATA_PIN">
                <shadow type="math_number">
                    <field name="NUM">0</field>
                </shadow>
            </value>
            <value name="CLOCK_PIN">
                <shadow type="math_number">
                    <field name="NUM">0</field>
                </shadow>
            </value>
        </block>
        <block type="advanced_io_shift_out">
            <value name="DATA_PIN">
                <shadow type="math_number">
                    <field name="NUM">0</field>
                </shadow>
            </value>
            <value name="CLOCK_PIN">
                <shadow type="math_number">
                    <field name="NUM">0</field>
                </shadow>
            </value>
            <value name="VALUE">
                <shadow type="math_number">
                    <field name="NUM">0</field>
                </shadow>
            </value>
        </block>
    </category>
    <category name="EEPROM" colour="#44a14f">
        <block type="eeprom_read">
            <value name="ADDRESS">
                <shadow type="math_number">
                    <field name="NUM">0</field>
                </shadow>
            </value>
        </block>
        <block type="eeprom_write">
            <value name="VALUE">
                <shadow type="math_number">
                    <field name="NUM">0</field>
                </shadow>
            </value>
            <value name="ADDRESS">
                <shadow type="math_number">
                    <field name="NUM">0</field>
                </shadow>
            </value>
        </block>
        <block type="eeprom_update">
            <value name="VALUE">
                <shadow type="math_number">
                    <field name="NUM">0</field>
                </shadow>
            </value>
            <value name="ADDRESS">
                <shadow type="math_number">
                    <field name="NUM">0</field>
                </shadow>
            </value>
        </block>
        <block type="eeprom_get">
            <value name="ADDRESS">
                <shadow type="math_number">
                    <field name="NUM">0</field>
                </shadow>
            </value>
            <value name="DATA">
                <shadow type="math_number">
                    <field name="NUM">0</field>
                </shadow>
            </value>
        </block>
        <block type="eeprom_put">
            <value name="VALUE">
                <shadow type="math_number">
                    <field name="NUM">0</field>
                </shadow>
            </value>
            <value name="ADDRESS">
                <shadow type="math_number">
                    <field name="NUM">0</field>
                </shadow>
            </value>
        </block>
    </category>
    <category name="SERVO" colour="#73a82b">
        <block type="servo_attach">
            <value name="PIN">
                <shadow type="math_number">
                    <field name="NUM">0</field>
                </shadow>
            </value>
            <value name="SERVO">
            </value>
        </block>
        <block type="servo_write">
            <value name="ANGLE">
                <shadow type="math_number">
                    <field name="NUM">0</field>
                </shadow>
            </value>
            <value name="SERVO">
            </value>
        </block>
        <block type="servo_write_microseconds">
            <value name="MICROS">
                <shadow type="math_number">
                    <field name="NUM">0</field>
                </shadow>
            </value>
            <value name="SERVO">
            </value>
        </block>
        <block type="servo_read">
            <value name="SERVO">
            </value>
        </block>
        <block type="servo_attached">
            <value name="SERVO">
            </value>
        </block>
        <block type="servo_detach">
            <value name="SERVO">
            </value>
        </block>
    </category>
    <category name="Serial" colour="#bfab36">
        <block type="text"></block>
        <block type="serial_begin">
            <value name="SPEED">
                <shadow type="math_number">
                    <field name="NUM">0</field>
                </shadow>
            </value>
        </block>
        <block type="serial_end"></block>
        <block type="serial_print_line">
            <value name="OUTPUT">
                <shadow type="text">
                    <field name="TEXT"></field>
                </shadow>
            </value>
        </block>
        <block type="serial_print">
            <value name="OUTPUT">
                <shadow type="text">
                    <field name="TEXT"></field>
                </shadow>
            </value>
        </block>
        <block type="serial_read"></block>
        <block type="serial_available"></block>
        <block type="serial_available_write"></block>
        <block type="serial_find">
            <value name="TARGET">
                <shadow type="text">
                    <field name="TEXT">targetString</field>
                </shadow>
            </value>
        </block>
        <block type="serial_find_until">
            <value name="TARGET">
                <shadow type="text">
                    <field name="TEXT">targetString</field>
                </shadow>
            </value>
            <value name="TERMINAL">
                <shadow type="text">
                    <field name="TEXT">terminalString</field>
                </shadow>
            </value>
        </block>
        <block type="serial_flush"></block>
        <block type="serial_parse_float"></block>
        <block type="serial_parse_int"></block>
        <block type="serial_peek"></block>
        <block type="serial_set_timeout">
            <value name="MILLISECONDS">
                <shadow type="math_number">
                    <field name="NUM">0</field>
                </shadow>
            </value>
        </block>
    </category>
    <category name="Constants" colour="#c08027">
        <block type="high"></block>
        <block type="low"></block>
        <block type="led_builtin"></block>
    </category>
    <category name="Utility" colour="#E03400">
        <block type="comment_oneline"></block>
    </category>
    <category name="String" colour="#bc1106">
        <block type="arduino_string_create">
            <value name="INPUT">
                <shadow type="text">
                    <field name="TEXT">defaultText</field>
                </shadow>
            </value>
        </block>
        <block type="arduino_string_create_base">
            <value name="INPUT">
                <shadow type="math_number">
                    <field name="NUM">0</field>
                </shadow>
            </value>
            <value name="BASE">
                <shadow type="math_number">
                    <field name="NUM">10</field>
                </shadow>
            </value>
        </block>
        <block type="arduino_string_char_at">
            <value name="LOCATION">
                <shadow type="math_number">
                    <field name="NUM">0</field>
                </shadow>
            </value>
            <value name="STRING">

            </value>
        </block>
        <block type="arduino_string_compare_to">
            <value name="LHS">

            </value>
            <value name="RHS">

            </value>
        </block>
        <block type="arduino_string_concat">
            <value name="STRING">

            </value>
            <value name="INPUT">

            </value>
        </block>
        <block type="arduino_string_ends_with">
            <value name="STRING">

            </value>
            <value name="INPUT">

            </value>
        </block>
        <block type="arduino_string_equals">
            <value name="LHS">

            </value>
            <value name="RHS">

            </value>

        </block>
        <block type="arduino_string_equals_ignore_case">
            <value name="LHS">

            </value>
            <value name="RHS">

            </value>

        </block>
        <block type="arduino_string_index_of">
            <value name="STRING">

            </value>
            <value name="INPUT">

            </value>
            <value name="POSITION">
                <shadow type="math_number">
                    <field name="NUM">0</field>
                </shadow>
            </value>
        </block>
        <block type="arduino_string_length">
            <value name="STRING">

            </value>
        </block>
        <block type="arduino_string_remove">
            <value name="STRING">

            </value>
            <value name="START">
                <shadow type="math_number">
                    <field name="NUM">0</field>
                </shadow>
            </value>
            <value name="END">
                <shadow type="math_number">
                    <field name="NUM">0</field>
                </shadow>
            </value>
        </block>
        <block type="arduino_string_replace">
            <value name="STRING">

            </value>
            <value name="LHS">
            </value>
            <value name="RHS">
            </value>
        </block>
        <block type="arduino_string_starts_with">
            <value name="LHS">

            </value>
            <value name="RHS">
            </value>
        </block>
        <block type="arduino_string_substring">
            <value name="STRING">

            </value>
            <value name="START">
                <shadow type="math_number">
                    <field name="NUM">0</field>
                </shadow>
            </value>
            <value name="END">
                <shadow type="math_number">
                    <field name="NUM">0</field>
                </shadow>
            </value>
        </block>
        <block type="arduino_string_to_int">
            <value name="STRING">

            </value>
        </block>
        <block type="arduino_string_to_float">
            <value name="STRING">

            </value>
        </block>
        <block type="arduino_string_to_lower">
            <value name="STRING">

            </value>
        </block>
        <block type="arduino_string_to_upper">
            <value name="STRING">

            </value>
        </block>
        <block type="arduino_string_trim">
            <value name="STRING">

            </value>
        </block>
    </category>
    <category name="Variables" colour="#381ECC" custom="VARIABLES_TYPED"/>
    <category name="Functions" colour="290" custom="PROCEDURE_TYPED"/>
    <sep></sep>
</xml>
